im_bored_pypi/__init__.py
im_bored_pypi/im_bored.py
im_bored-0.1.0.dist-info/METADATA
im_bored-0.1.0.dist-info/WHEEL
im_bored-0.1.0.dist-info/top_level.txt
im_bored-0.1.0.dist-info/RECORD
